I2C_master1.v
module I2C_master1 (
    input wire clk,
    input wire reset,
    input wire enable,
    input wire [7:0] data_in,
    input wire [6:0] ext_slave_addr,
    input wire [7:0] ext_reg_addr,
    input wire read_write,
    
    //  output wire  scl,
    //  output wire SDA_out,
     input wire SDA_in                                                                                                                                                                                                                                                                                                                                                                                                                                                                                                                                                                                                                                                                                                                                                                                                                                                                                                                                                                                   
);
     reg scl,SDA_out =1'b1;
     reg scl_counter=1'b0;


    localparam IDLE = 3'b000;
    localparam START = 3'b001;
    localparam ADDRESS = 3'b010;
    localparam r_w = 3'b011;
    localparam ADD_ACK_NACK =3'B100;
    localparam DATA =3'b101 ;
    localparam DATA_ACK_NACK=3'b110 ;
    localparam STOP = 3'b111;      

    reg [2:0] state, nextstate;
    reg [6:0] shiftreg = 7'b0;
    always @(negedge clk ) begin
        scl_counter <= scl_counter + 1;
    end
    always @(posedge clk) begin
        
        if (reset) begin
            state <= IDLE;
            
        end
        else begin
            state <= nextstate;


        end
    end    
    always @(*)begin
        case (state)
            IDLE: begin
                if (enable) begin
                    scl=1'b1;
                    SDA_out=1'b1;
                    nextstate = START;
                    shiftreg =ext_slave_addr;
                end
            end
            START: begin
                SDA_out <= 1'b0;
                if(scl_counter==0)begin
                    scl <= 1'b0;
                    
                end
               
                nextstate = ADDRESS;
                
            end
            
            ADDRESS: begin

                 SDA_out <= shiftreg[7];
                    shiftreg = {shiftreg[6:0], 1'b0};
                nextstate = IDLE;
            end
        endcase
    end                                                                                                                                                                                                                                                                                                                                       
    
endmodule

I2C_master1_tb.v
`timescale 1ns/1ns

module I2C_master1_tb;

    // Parameters
    parameter CLK_PERIOD = 10; // Clock period in ns

    // Inputs
    reg clk;
    reg reset;
    reg enable;
    reg [7:0] data_in;
    reg [6:0] ext_slave_addr;
    reg [7:0] ext_reg_addr;
    reg read_write;
    reg SDA_in;
    
    // Outputs
    wire SDA_out;
    wire scl;

    // Instantiate the I2c_master1 module
    I2C_master1 u_I2C_master1 (
        .clk(clk),
        .reset(reset),
        .enable(enable),
        .data_in(data_in),
        .ext_slave_addr(ext_slave_addr),
        .ext_reg_addr(ext_reg_addr),
        .read_write(read_write),
        //.SDA_out(SDA_out), // commented out to prevent redeclaration error
        //.scl(scl),         // commented out to prevent redeclaration error
        .SDA_in(SDA_in)
    );

   initial begin
    clk = 1;
    forever #5 clk = ~clk;
  end
    // Dumping waveform
    initial begin
        $dumpfile("I2C_master1.vcd");
        $dumpvars(0, I2C_master1_tb);
        
        // Stimulus generation
        // Initialize inputs
        clk = 1;
        ext_slave_addr=7'b1101001;
        reset = 1'b1;
        enable = 1'b1;
        data_in = 8'b0;
        ext_slave_addr = 7'b0;
        ext_reg_addr = 8'b0;
        read_write = 1'b0;
        SDA_in = 1'b0;

        // Reset
        #10 reset = 1'b0;

        // Enable
       // #10 enable = 1'b1;

        // Test scenario
        // You can modify this part to simulate different test scenarios
        // Here, we are just asserting enable and observing the output
        // You should expand this to cover various scenarios of your design

        // Scenario 1: Enable asserted
        #100;
        $display("Scenario 1: Enable asserted");
        enable = 1'b0;
        // Add more test scenarios here...

        // End simulation
        #100;
        $finish;
    end

endmodule

I2C_master1.vcd
$date
	Sat Mar 30 02:36:20 2024
$end
$version
	Icarus Verilog
$end
$timescale
	1ns
$end
$scope module I2C_master1_tb $end
$var parameter 32 ! CLK_PERIOD $end
$var reg 1 " SDA_in $end
$var reg 1 # clk $end
$var reg 8 $ data_in [7:0] $end
$var reg 1 % enable $end
$var reg 8 & ext_reg_addr [7:0] $end
$var reg 7 ' ext_slave_addr [6:0] $end
$var reg 1 ( read_write $end
$var reg 1 ) reset $end
$scope module u_I2C_master1 $end
$var wire 1 " SDA_in $end
$var wire 1 # clk $end
$var wire 8 * data_in [7:0] $end
$var wire 1 % enable $end
$var wire 8 + ext_reg_addr [7:0] $end
$var wire 7 , ext_slave_addr [6:0] $end
$var wire 1 ( read_write $end
$var wire 1 ) reset $end
$var parameter 3 - ADDRESS $end
$var parameter 3 . ADD_ACK_NACK $end
$var parameter 3 / DATA $end
$var parameter 3 0 DATA_ACK_NACK $end
$var parameter 3 1 IDLE $end
$var parameter 3 2 START $end
$var parameter 3 3 STOP $end
$var parameter 3 4 r_w $end
$var reg 1 5 SDA_out $end
$var reg 3 6 nextstate [2:0] $end
$var reg 1 7 scl $end
$var reg 1 8 scl_counter $end
$var reg 7 9 shiftreg [6:0] $end
$var reg 3 : state [2:0] $end
$upscope $end
$upscope $end
$enddefinitions $end
$comment Show the parameter values. $end
$dumpall
b11 4
b111 3
b1 2
b0 1
b110 0
b101 /
b100 .
b10 -
b1010 !
$end
#0
$dumpvars
b0 :
b0 9
08
17
b1 6
15
b0 ,
b0 +
b0 *
1)
0(
b0 '
b0 &
1%
b0 $
1#
0"
$end
#5
18
0#
#10
05
b10 6
b1 :
1#
0)
#15
07
08
0#
#20
x5
b0 6
b10 :
1#
#25
18
0#
#30
b1 6
15
17
b0 :
1#
#35
08
0#
#40
07
05
b10 6
b1 :
1#
#45
18
0#
#50
x5
b0 6
b10 :
1#
#55
08
0#
#60
b1 6
15
17
b0 :
1#
#65
18
0#
#70
05
b10 6
b1 :
1#
#75
07
08
0#
#80
x5
b0 6
b10 :
1#
#85
18
0#
#90
b1 6
15
17
b0 :
1#
#95
08
0#
#100
07
05
b10 6
b1 :
1#
#105
18
0#
#110
x5
b0 6
b10 :
1#
0%
#115
08
0#
#120
b0 :
1#
#125
18
0#
#130
1#
#135
08
0#
#140
1#
#145
18
0#
#150
1#
#155
08
0#
#160
1#
#165
18
0#
#170
1#
#175
08
0#
#180
1#
#185
18
0#
#190
1#
#195
08
0#
#200
1#
#205
18
0#
