I2C_master1.sv
module I2C_master1 (
    input logic clk,
    input logic reset,
    input logic enable,
    input logic [7:0] data_in,
    input logic [6:0] ext_slave_addr,
    input logic [7:0] ext_reg_addr,
    input logic read_write,
    input logic add_Ack,
    input logic reg_Ack,
    input logic data_Ack,

    input logic SDA_in
);
    logic scl, SDA_out;
    logic scl_counter = 1'b0;

    localparam IDLE = 4'b0000;
    localparam START = 4'b0001;
    localparam ADDRESS = 4'b0010;
    localparam r_w = 4'b0011;
    localparam ADD_ACK_NACK = 4'b0100;
    localparam slave_reg = 4'b0101;
    localparam reg_ACK_NACK = 4'b0110;
    localparam DATA = 4'b0111;
    localparam DATA_ACK_NACK = 4'b1000;
    localparam STOP = 4'b1001;

    logic [3:0] state, nextstate;
    logic [6:0] shiftreg;
    logic [7:0] shiftreg1, shiftreg2;
    logic [3:0] reg_add_counter, data_add_counter = 4'b000;
    logic [2:0] addcounter = 3'b000;

    always_ff @(posedge clk or posedge reset) begin
        if (reset) begin
            state <= IDLE;
            // shiftreg = ext_slave_addr;
            // shiftreg1 = ext_reg_addr;
        end else begin
            state <= nextstate;
        end
    end

    always_ff @(posedge clk) begin
        scl_counter <= scl_counter + 1;
    end

    always_comb begin
        case (state)
            IDLE: begin
                if (enable) begin
                    scl = 1'b1;
                    SDA_out = 1'b1;
                    nextstate = START;
                    addcounter = 3'b000;
                end
            end
            START: begin
                SDA_out = 1'b0;
                shiftreg = ext_slave_addr;
                shiftreg1 = ext_reg_addr;
                shiftreg2 = data_in;
                if (scl_counter == 0) begin
                    scl = 1'b0;
                end
                addcounter = 3'b000;
                nextstate = ADDRESS;
            end
            ADDRESS: begin
                scl = scl_counter;
                if (scl_counter == 1) begin
                    addcounter = addcounter + 1;
                    SDA_out = shiftreg[7];
                    shiftreg = {shiftreg[6:0], 1'b0};
                end
                if (addcounter == 3'b111) begin
                    nextstate = r_w;
                    addcounter = 3'b000;
                end
            end
            r_w: begin
                scl = scl_counter;
                nextstate = ADD_ACK_NACK;
            end
            ADD_ACK_NACK: begin
                scl = scl_counter;
                if (add_Ack) begin
                    nextstate = slave_reg;
                end
                reg_add_counter = 3'b000;
            end
            slave_reg: begin
                scl = scl_counter;
                if (scl_counter == 0) begin
                    reg_add_counter = reg_add_counter + 1;
                    SDA_out = shiftreg1[7];
                    shiftreg1 = {shiftreg1[6:0], 1'b0};
                end
                if (reg_add_counter == 4'b1001) begin
                    nextstate = reg_ACK_NACK;
                    reg_add_counter = 3'b000;
                end
            end
            reg_ACK_NACK: begin
                scl = scl_counter;
                if (reg_Ack) begin
                    nextstate = DATA;
                end
            end
            DATA: begin
                scl = scl_counter;
                if (scl_counter == 0) begin
                    data_add_counter = data_add_counter + 1;
                    if (read_write) begin
                        SDA_out = shiftreg2[7];
                        shiftreg2 = {shiftreg2[6:0], 1'b0};
                    end
                    if (data_add_counter == 3'b111) begin
                        nextstate = DATA_ACK_NACK;
                        data_add_counter = 3'b000;
                    end
                end
            end
            DATA_ACK_NACK: begin
                scl = scl_counter;
                if (data_Ack) begin
                    nextstate = STOP;
                    scl = 1'b0;
                    SDA_out = 1'b0;
                end
            end
            STOP: begin
                scl = 1'b1;
                if (scl_counter == 0) begin
                    SDA_out = 1'b1;
                end
            end
        endcase
    end
endmodule

I2C_master1_tb.v
`timescale 1ns/1ns

module I2C_master1_tb;

    // Parameters
    parameter CLK_PERIOD = 10; // Clock period in ns

    // Inputs
    reg clk;
    reg reset;
    reg enable;
    reg [7:0] data_in;
    reg [6:0] ext_slave_addr;
    reg [7:0] ext_reg_addr;
    reg add_Ack;
    reg reg_Ack;
    reg data_Ack;
    reg read_write;
    reg SDA_in;
    
    // Outputs
    wire SDA_out;
    wire scl;

    // Instantiate the I2c_master1 module
    I2C_master1 u_I2C_master1 (
        .clk(clk),
        .reset(reset),
        .enable(enable),
        .data_in(data_in),
        .ext_slave_addr(ext_slave_addr),
        .ext_reg_addr(ext_reg_addr),
    //    .ext_data(ext_data),   
        .read_write(read_write),
        .add_Ack(add_Ack),
        .reg_Ack(reg_Ack),
        .data_Ack(data_Ack),
        //.SDA_out(SDA_out), // commented out to prevent redeclaration error
        //.scl(scl),         // commented out to prevent redeclaration error
        .SDA_in(SDA_in)
    );

   initial begin
    clk = 1;
    forever #5 clk = ~clk;
  end
    // Dumping waveform
    initial begin
        $dumpfile("I2C_master1.vcd");
        $dumpvars(0, I2C_master1_tb);
        
        // Stimulus generation
        // Initialize inputs
        clk = 1;
        ext_slave_addr=7'b1101001;
        reset = 1'b1;
        enable = 1'b1;
        add_Ack = 1'b1;
        reg_Ack = 1'b1;
        data_Ack = 1'b1;
        data_in = 8'b0;
        ext_slave_addr = 7'b1101001;
        ext_reg_addr = 8'b11111011;
        data_in = 8'b10101010;
        read_write = 1'b1;
        SDA_in = 1'b0;

        // Reset
        #10 reset = 1'b0;

        // Enable
       // #10 enable = 1'b1;

        // Test scenario
        // You can modify this part to simulate different test scenarios
        // Here, we are just asserting enable and observing the output
        // You should expand this to cover various scenarios of your design

        // Scenario 1: Enable asserted
        #100;
        $display("Scenario 1: Enable asserted");
        //enable = 1'b0;
        // Add more test scenarios here...

        // End simulation
        #700;
        $finish;
    end

endmodule

I2C_master1.vcd
$date
	Thu May  2 00:09:33 2024
$end
$version
	Icarus Verilog
$end
$timescale
	1ns
$end
$scope module I2C_master1_tb $end
$var parameter 32 ! CLK_PERIOD $end
$var reg 1 " SDA_in $end
$var reg 1 # add_Ack $end
$var reg 1 $ clk $end
$var reg 1 % data_Ack $end
$var reg 8 & data_in [7:0] $end
$var reg 1 ' enable $end
$var reg 8 ( ext_reg_addr [7:0] $end
$var reg 7 ) ext_slave_addr [6:0] $end
$var reg 1 * read_write $end
$var reg 1 + reg_Ack $end
$var reg 1 , reset $end
$scope module u_I2C_master1 $end
$var wire 1 " SDA_in $end
$var wire 1 # add_Ack $end
$var wire 1 $ clk $end
$var wire 1 % data_Ack $end
$var wire 8 - data_in [7:0] $end
$var wire 1 ' enable $end
$var wire 8 . ext_reg_addr [7:0] $end
$var wire 7 / ext_slave_addr [6:0] $end
$var wire 1 * read_write $end
$var wire 1 + reg_Ack $end
$var wire 1 , reset $end
$var parameter 4 0 ADDRESS $end
$var parameter 4 1 ADD_ACK_NACK $end
$var parameter 4 2 DATA $end
$var parameter 4 3 DATA_ACK_NACK $end
$var parameter 4 4 IDLE $end
$var parameter 4 5 START $end
$var parameter 4 6 STOP $end
$var parameter 4 7 r_w $end
$var parameter 4 8 reg_ACK_NACK $end
$var parameter 4 9 slave_reg $end
$var reg 1 : SDA_out $end
$var reg 3 ; addcounter [2:0] $end
$var reg 4 < data_add_counter [3:0] $end
$var reg 4 = nextstate [3:0] $end
$var reg 4 > reg_add_counter [3:0] $end
$var reg 1 ? scl $end
$var reg 1 @ scl_counter $end
$var reg 7 A shiftreg [6:0] $end
$var reg 8 B shiftreg1 [7:0] $end
$var reg 8 C shiftreg2 [7:0] $end
$var reg 4 D state [3:0] $end
$upscope $end
$upscope $end
$enddefinitions $end
$comment Show the parameter values. $end
$dumpall
b101 9
b110 8
b11 7
b1001 6
b1 5
b0 4
b1000 3
b111 2
b100 1
b10 0
b1010 !
$end
#0
$dumpvars
b0 D
bx C
bx B
bx A
0@
1?
bx >
b1 =
b0 <
b0 ;
1:
b1101001 /
b11111011 .
b10101010 -
1,
1+
1*
b1101001 )
b11111011 (
1'
b10101010 &
1%
1$
1#
0"
$end
#5
1@
0$
#10
0:
b10 =
b10101010 C
b11111011 B
b1101001 A
b1 D
1$
0,
#15
0?
0@
0$
#20
b10 D
1$
#25
x:
b1010010 A
b1 ;
1?
1@
0$
#30
1$
#35
0?
0@
0$
#40
1$
#45
b100100 A
b10 ;
1?
1@
0$
#50
1$
#55
0?
0@
0$
#60
1$
#65
b1001000 A
b11 ;
1?
1@
0$
#70
1$
#75
0?
0@
0$
#80
1$
#85
b10000 A
b100 ;
1?
1@
0$
#90
1$
#95
0?
0@
0$
#100
1$
#105
b100000 A
b101 ;
1?
1@
0$
#110
1$
#115
0?
0@
0$
#120
1$
#125
b1000000 A
b110 ;
1?
1@
0$
#130
1$
#135
0?
0@
0$
#140
1$
#145
b11 =
b0 A
b0 ;
1?
1@
0$
#150
b100 =
b11 D
1$
#155
0?
0@
0$
#160
b0 >
b101 =
b100 D
1$
#165
1?
1@
0$
#170
b101 D
1$
#175
1:
b11110110 B
b1 >
0?
0@
0$
#180
1$
#185
1?
1@
0$
#190
1$
#195
b11101100 B
b10 >
0?
0@
0$
#200
1$
#205
1?
1@
0$
#210
1$
#215
b11011000 B
b11 >
0?
0@
0$
#220
1$
#225
1?
1@
0$
#230
1$
#235
b10110000 B
b100 >
0?
0@
0$
#240
1$
#245
1?
1@
0$
#250
1$
#255
b1100000 B
b101 >
0?
0@
0$
#260
1$
#265
1?
1@
0$
#270
1$
#275
0:
b11000000 B
b110 >
0?
0@
0$
#280
1$
#285
1?
1@
0$
#290
1$
#295
1:
b10000000 B
b111 >
0?
0@
0$
#300
1$
#305
1?
1@
0$
#310
1$
#315
b0 B
b1000 >
0?
0@
0$
#320
1$
#325
1?
1@
0$
#330
1$
#335
0:
b110 =
b0 >
0?
0@
0$
#340
b111 =
b110 D
1$
#345
1?
1@
0$
#350
b111 D
1$
#355
1:
b1010100 C
b1 <
0?
0@
0$
#360
1$
#365
1?
1@
0$
#370
1$
#375
0:
b10101000 C
b10 <
0?
0@
0$
#380
1$
#385
1?
1@
0$
#390
1$
#395
1:
b1010000 C
b11 <
0?
0@
0$
#400
1$
#405
1?
1@
0$
#410
1$
#415
0:
b10100000 C
b100 <
0?
0@
0$
#420
1$
#425
1?
1@
0$
#430
1$
#435
1:
b1000000 C
b101 <
0?
0@
0$
#440
1$
#445
1?
1@
0$
#450
1$
#455
0:
b10000000 C
b110 <
0?
0@
0$
#460
1$
#465
1?
1@
0$
#470
1$
#475
1:
b1000 =
b0 C
b0 <
0?
0@
0$
#480
0:
b1001 =
b1000 D
1$
#485
0?
1@
0$
#490
1?
b1001 D
1$
#495
1:
0@
0$
#500
1$
#505
1@
0$
#510
1$
#515
0@
0$
#520
1$
#525
1@
0$
#530
1$
#535
0@
0$
#540
1$
#545
1@
0$
#550
1$
#555
0@
0$
#560
1$
#565
1@
0$
#570
1$
#575
0@
0$
#580
1$
#585
1@
0$
#590
1$
#595
0@
0$
#600
1$
#605
1@
0$
#610
1$
#615
0@
0$
#620
1$
#625
1@
0$
#630
1$
#635
0@
0$
#640
1$
#645
1@
0$
#650
1$
#655
0@
0$
#660
1$
#665
1@
0$
#670
1$
#675
0@
0$
#680
1$
#685
1@
0$
#690
1$
#695
0@
0$
#700
1$
#705
1@
0$
#710
1$
#715
0@
0$
#720
1$
#725
1@
0$
#730
1$
#735
0@
0$
#740
1$
#745
1@
0$
#750
1$
#755
0@
0$
#760
1$
#765
1@
0$
#770
1$
#775
0@
0$
#780
1$
#785
1@
0$
#790
1$
#795
0@
0$
#800
1$
#805
1@
0$
