I2C_master1.v
module I2C_master1 (
    input wire clk,
    input wire reset,
    input wire enable,
    input wire [7:0] data_in,
    input wire [6:0] ext_slave_addr,
    input wire [7:0] ext_reg_addr,
   // input wire [7:0] ext_data,
    input wire read_write,
    input wire add_Ack,
    input wire reg_Ack,
    input wire data_Ack,

    //  output wire  scl,
    //  output wire SDA_out,
     input wire SDA_in                                                                                                                                                                                                                                                                                                                                                                                                                                                                                                                                                                                                                                                                                                                                                                                                                                                                                                                                                                                   
);
     reg scl,SDA_out =1'b1;
     reg scl_counter=1'b0;


    localparam IDLE = 4'b0000;
    localparam START = 4'b0001;
    localparam ADDRESS = 4'b0010;
    localparam r_w = 4'b0011;
    localparam ADD_ACK_NACK =4'B0100;
    localparam slave_reg =4'b0101 ;
    localparam reg_ACK_NACK=4'b0110 ;
    localparam DATA=4'b0111 ;
    localparam DATA_ACK_NACK=4'b1000 ;
    localparam STOP = 4'b1001;      

    reg [3:0] state, nextstate;
    reg [6:0] shiftreg,shiftreg1 ;
    reg [2:0] reg_add_counter=3'b000;
    reg [2:0] addcounter,data_add_counter = 3'b000;

    always @(negedge clk ) begin
        scl_counter <= scl_counter + 1;
    end
    always @(posedge clk) begin
        // addcounter <= addcounter + 1;
        if (reset) begin
            state <= IDLE;
            
        end
        else begin
            state <= nextstate;


        end
    end    
    always @(*)begin
        case (state)
            IDLE: begin
                if (enable) begin
                    scl=1'b1;
                    SDA_out=1'b1;
                    nextstate = START;
                   addcounter = 3'b000;

                end
                
                 
            end
            START: begin
                SDA_out <= 1'b0;
                 shiftreg =ext_slave_addr;
                 shiftreg1=ext_reg_addr;
                if(scl_counter==0)begin
                    scl <= 1'b0;
                    
                end
               addcounter=3'b000;
                nextstate = ADDRESS;
                
            end
            
            ADDRESS: begin
                if(scl_counter==1) begin
                    addcounter = addcounter + 1;

                end

                 SDA_out <= shiftreg[7];
                    shiftreg = {shiftreg[6:0], 1'b0};
                // nextstate = IDLE;

                 if (addcounter == 3'b111) begin
                    nextstate = r_w;
                    addcounter = 3'b000;
                end
                
            end
            r_w: begin
                if (read_write) begin
                   nextstate=ADD_ACK_NACK; 
                end
            
    
            end 

            ADD_ACK_NACK: begin
                if (add_Ack) begin
                    nextstate = slave_reg;
                   
                end
                reg_add_counter = 3'b000;
            end


            slave_reg:begin
                
              if(scl_counter==1) begin
                    reg_add_counter = reg_add_counter + 1;

                end


                 if (reg_add_counter == 3'b111) begin
                    nextstate = reg_ACK_NACK;
                    reg_add_counter = 3'b000;
                end
            end
             reg_ACK_NACK: begin
                if (reg_Ack) begin
                    nextstate = DATA;
                   
                end
             end
            DATA: begin
                if(scl_counter==1) begin
                    data_add_counter = data_add_counter + 1;

                end

             
                 if (data_add_counter == 3'b111) begin
                    nextstate = DATA_ACK_NACK;
                    data_add_counter = 3'b000;
                end
                
            end
            DATA_ACK_NACK: begin
                if (data_Ack) begin
                    nextstate = STOP;
                   
                end
            end
             STOP: begin    
                scl <= 1'b1;
                 
                if(scl_counter==0)begin
                    SDA_out <= 1'b1;
                    
                end
             end
        endcase
    end                                                                                                                                                                                                                                                                                                                                       
    
endmodule

// iverilog -o I2C_master1.out I2C_master1.v I2C_master1_tb.v
// vvp I2C_master1.out
// gtkwave I2C_master1.vcd

I2C_master1_tb.v
`timescale 1ns/1ns

module I2C_master1_tb;

    // Parameters
    parameter CLK_PERIOD = 10; // Clock period in ns

    // Inputs
    reg clk;
    reg reset;
    reg enable;
    reg [7:0] data_in;
    reg [6:0] ext_slave_addr;
    reg [7:0] ext_reg_addr;
    reg add_Ack;
    reg reg_Ack;
    reg data_Ack;
    reg read_write;
    reg SDA_in;
    
    // Outputs
    wire SDA_out;
    wire scl;

    // Instantiate the I2c_master1 module
    I2C_master1 u_I2C_master1 (
        .clk(clk),
        .reset(reset),
        .enable(enable),
        .data_in(data_in),
        .ext_slave_addr(ext_slave_addr),
        .ext_reg_addr(ext_reg_addr),
    //    .ext_data(ext_data),   
        .read_write(read_write),
        .add_Ack(add_Ack),
        .reg_Ack(reg_Ack),
        .data_Ack(data_Ack),
        //.SDA_out(SDA_out), // commented out to prevent redeclaration error
        //.scl(scl),         // commented out to prevent redeclaration error
        .SDA_in(SDA_in)
    );

   initial begin
    clk = 1;
    forever #5 clk = ~clk;
  end
    // Dumping waveform
    initial begin
        $dumpfile("I2C_master1.vcd");
        $dumpvars(0, I2C_master1_tb);
        
        // Stimulus generation
        // Initialize inputs
        clk = 1;
        ext_slave_addr=7'b1101001;
        reset = 1'b1;
        enable = 1'b1;
        add_Ack = 1'b1;
        reg_Ack = 1'b1;
        data_Ack = 1'b1;
        data_in = 8'b0;
        ext_slave_addr = 7'b0;
        ext_reg_addr = 8'b0;
        read_write = 1'b1;
        SDA_in = 1'b0;

        // Reset
        #10 reset = 1'b0;

        // Enable
       // #10 enable = 1'b1;

        // Test scenario
        // You can modify this part to simulate different test scenarios
        // Here, we are just asserting enable and observing the output
        // You should expand this to cover various scenarios of your design

        // Scenario 1: Enable asserted
        #100;
        $display("Scenario 1: Enable asserted");
        //enable = 1'b0;
        // Add more test scenarios here...

        // End simulation
        #400;
        $finish;
    end

endmodule

I2C_master1.vcd
$date
	Tue Apr  2 00:20:56 2024
$end
$version
	Icarus Verilog
$end
$timescale
	1ns
$end
$scope module I2C_master1_tb $end
$var parameter 32 ! CLK_PERIOD $end
$var reg 1 " SDA_in $end
$var reg 1 # add_Ack $end
$var reg 1 $ clk $end
$var reg 1 % data_Ack $end
$var reg 8 & data_in [7:0] $end
$var reg 1 ' enable $end
$var reg 8 ( ext_reg_addr [7:0] $end
$var reg 7 ) ext_slave_addr [6:0] $end
$var reg 1 * read_write $end
$var reg 1 + reg_Ack $end
$var reg 1 , reset $end
$scope module u_I2C_master1 $end
$var wire 1 " SDA_in $end
$var wire 1 # add_Ack $end
$var wire 1 $ clk $end
$var wire 1 % data_Ack $end
$var wire 8 - data_in [7:0] $end
$var wire 1 ' enable $end
$var wire 8 . ext_reg_addr [7:0] $end
$var wire 7 / ext_slave_addr [6:0] $end
$var wire 1 * read_write $end
$var wire 1 + reg_Ack $end
$var wire 1 , reset $end
$var parameter 4 0 ADDRESS $end
$var parameter 4 1 ADD_ACK_NACK $end
$var parameter 4 2 DATA $end
$var parameter 4 3 DATA_ACK_NACK $end
$var parameter 4 4 IDLE $end
$var parameter 4 5 START $end
$var parameter 4 6 STOP $end
$var parameter 4 7 r_w $end
$var parameter 4 8 reg_ACK_NACK $end
$var parameter 4 9 slave_reg $end
$var reg 1 : SDA_out $end
$var reg 3 ; addcounter [2:0] $end
$var reg 3 < data_add_counter [2:0] $end
$var reg 4 = nextstate [3:0] $end
$var reg 3 > reg_add_counter [2:0] $end
$var reg 1 ? scl $end
$var reg 1 @ scl_counter $end
$var reg 7 A shiftreg [6:0] $end
$var reg 7 B shiftreg1 [6:0] $end
$var reg 4 C state [3:0] $end
$upscope $end
$upscope $end
$enddefinitions $end
$comment Show the parameter values. $end
$dumpall
b101 9
b110 8
b11 7
b1001 6
b1 5
b0 4
b1000 3
b111 2
b100 1
b10 0
b1010 !
$end
#0
$dumpvars
b0 C
bx B
bx A
0@
1?
b0 >
b1 =
b0 <
b0 ;
1:
b0 /
b0 .
b0 -
1,
1+
1*
b0 )
b0 (
1'
b0 &
1%
1$
1#
0"
$end
#5
1@
0$
#10
0:
b10 =
b0 B
b0 A
b1 C
1$
0,
#15
0?
0@
0$
#20
x:
b10 C
1$
#25
b1 ;
1@
0$
#30
1$
#35
0@
0$
#40
1$
#45
b10 ;
1@
0$
#50
1$
#55
0@
0$
#60
1$
#65
b11 ;
1@
0$
#70
1$
#75
0@
0$
#80
1$
#85
b100 ;
1@
0$
#90
1$
#95
0@
0$
#100
1$
#105
b101 ;
1@
0$
#110
1$
#115
0@
0$
#120
1$
#125
b110 ;
1@
0$
#130
1$
#135
0@
0$
#140
1$
#145
b11 =
b0 ;
1@
0$
#150
b100 =
b11 C
1$
#155
0@
0$
#160
b101 =
b100 C
1$
#165
1@
0$
#170
b1 >
b101 C
1$
#175
0@
0$
#180
1$
#185
b10 >
1@
0$
#190
1$
#195
0@
0$
#200
1$
#205
b11 >
1@
0$
#210
1$
#215
0@
0$
#220
1$
#225
b100 >
1@
0$
#230
1$
#235
0@
0$
#240
1$
#245
b101 >
1@
0$
#250
1$
#255
0@
0$
#260
1$
#265
b110 >
1@
0$
#270
1$
#275
0@
0$
#280
1$
#285
b110 =
b0 >
1@
0$
#290
b111 =
b110 C
1$
#295
0@
0$
#300
b111 C
1$
#305
b1 <
1@
0$
#310
1$
#315
0@
0$
#320
1$
#325
b10 <
1@
0$
#330
1$
#335
0@
0$
#340
1$
#345
b11 <
1@
0$
#350
1$
#355
0@
0$
#360
1$
#365
b100 <
1@
0$
#370
1$
#375
0@
0$
#380
1$
#385
b101 <
1@
0$
#390
1$
#395
0@
0$
#400
1$
#405
b110 <
1@
0$
#410
1$
#415
0@
0$
#420
1$
#425
b1000 =
b0 <
1@
0$
#430
b1001 =
b1000 C
1$
#435
0@
0$
#440
1:
1?
b1001 C
1$
#445
1@
0$
#450
1$
#455
0@
0$
#460
1$
#465
1@
0$
#470
1$
#475
0@
0$
#480
1$
#485
1@
0$
#490
1$
#495
0@
0$
#500
1$
#505
1@
0$
